[
{ "abbreviation": "AT", "name": "Austria" },
{ "abbreviation": "BE", "name": "Belgium" },
{ "abbreviation": "BG", "name": "Bulgaria" },
{ "abbreviation": "CY", "name": "Cyprus" },
{ "abbreviation": "CZ", "name": "Czech Republic" },
{ "abbreviation": "DE", "name": "Germany" },
{ "abbreviation": "DK", "name": "Denmark" },
{ "abbreviation": "EE", "name": "Estonia" },
{ "abbreviation": "GR", "name": "Greece" },
{ "abbreviation": "ES", "name": "Spain" },
{ "abbreviation": "FI", "name": "Finland" },
{ "abbreviation": "FR", "name": "France" },
{ "abbreviation": "HR", "name": "Croatia" },
{ "abbreviation": "HU", "name": "Hungary" },
{ "abbreviation": "IE", "name": "Ireland" },
{ "abbreviation": "IT", "name": "Italy" },
{ "abbreviation": "LT", "name": "Lithuania" },
{ "abbreviation": "LU", "name": "Luxembourg" },
{ "abbreviation": "LV", "name": "Latvia" },
{ "abbreviation": "MT", "name": "Malta" },
{ "abbreviation": "NL", "name": "Netherlands" },
{ "abbreviation": "PL", "name": "Poland" },
{ "abbreviation": "PT", "name": "Portugal" },
{ "abbreviation": "RO", "name": "Romania" },
{ "abbreviation": "SE", "name": "Sweden" },
{ "abbreviation": "SI", "name": "Slovenia" },
{ "abbreviation": "SK", "name": "Slovakia" },
{ "abbreviation": "UK", "name": "United Kingdom" }
]
